README.md
setup.py
tess_waldo/__init__.py
tess_waldo/waldo.py
tess_waldo.egg-info/PKG-INFO
tess_waldo.egg-info/SOURCES.txt
tess_waldo.egg-info/dependency_links.txt
tess_waldo.egg-info/requires.txt
tess_waldo.egg-info/top_level.txt