Metadata-Version: 1.0
Name: tess-waldo
Version: 1.0.1
Summary: A friendly package for finding targets on TESS CCDs.
Home-page: UNKNOWN
Author: Simon J. Murphy
Author-email: simon.murphy@sydney.edu.au
License: MIT
Platform: UNKNOWN
